Metadata-Version: 1.1
Name: apiblueprint-codec
Version: 0.0.1
Summary: An API Blueprint codec for Core API.
Home-page: http://github.com/encode/apiblueprint-codec/
Author: Tom Christie
Author-email: tom@tomchristie.com
License: BSD
Platform: UNKNOWN
Classifier: Intended Audience :: Developers
Classifier: License :: OSI Approved :: BSD License
Classifier: Operating System :: OS Independent
Classifier: Programming Language :: Python
Classifier: Programming Language :: Python :: 3
